Metadata-Version: 1.0
Name: AutomaticGraphs
Version: 0.2.3
Summary: Plot graphs faster with seaborn
Home-page: UNKNOWN
Author: UNKNOWN
Author-email: UNKNOWN
License: UNKNOWN
Platform: UNKNOWN
